async_hvac/__init__.py
async_hvac/aws_utils.py
async_hvac/exceptions.py
async_hvac/v1/__init__.py
async_hvac-0.7.3.dist-info/licenses/LICENSE.txt
async_hvac-0.7.3.dist-info/METADATA
async_hvac-0.7.3.dist-info/WHEEL
async_hvac-0.7.3.dist-info/top_level.txt
async_hvac-0.7.3.dist-info/RECORD
