Metadata-Version: 2.4
Name: async-hvac
Version: 0.7.3
Summary: HashiCorp Vault API python 3.9+ client using asyncio.
Home-page: https://github.com/jamaalscarlett/async-hvac
Download-URL: https://github.com/jamaalscarlett/async-hvac/tarball/master
Author: Lionel Zerbib
Author-email: lionel@alooma.io
Maintainer: Jamaal Scarlett
Maintainer-email: jamaalscarlett.github@gmail.com
Keywords: hashicorp,vault,hvac
Classifier: Development Status :: 5 - Production/Stable
Classifier: License :: OSI Approved :: Apache Software License
Classifier: Intended Audience :: Developers
Classifier: Programming Language :: Python :: 3
Classifier: Programming Language :: Python :: 3.9
Classifier: Programming Language :: Python :: 3.10
Classifier: Programming Language :: Python :: 3.11
Classifier: Programming Language :: Python :: 3.12
Classifier: Programming Language :: Python :: 3.13
Classifier: Programming Language :: Python :: 3.14
Requires-Python: >=3.9
License-File: LICENSE.txt
Requires-Dist: aiohttp>=3.3.1
Provides-Extra: parser
Requires-Dist: pyhcl>=0.4.5; extra == "parser"
Dynamic: download-url
Dynamic: license-file
